nael_utils/__init__.py
nael_utils/anthropic_ext.py
nael_utils/decorators.py
nael_utils/deeper_validate.py
nael_utils/langchain_ext.py
nael_utils/py.typed
nael_utils-0.1.13.dist-info/METADATA
nael_utils-0.1.13.dist-info/WHEEL
nael_utils-0.1.13.dist-info/top_level.txt
nael_utils-0.1.13.dist-info/RECORD
